setup.py
django_markup_tags.egg-info/PKG-INFO
django_markup_tags.egg-info/SOURCES.txt
django_markup_tags.egg-info/dependency_links.txt
django_markup_tags.egg-info/top_level.txt
markuptags/__init__.py
markuptags/templatetags/__init__.py
markuptags/templatetags/markuptags.py