Metadata-Version: 1.0
Name: django-markup-tags
Version: 0.1.1
Summary: Template tags (not filters) for Markdown, Textile, and ReST.
Home-page: https://github.com/readevalprint/django-markup-tags
Author: Timothy Watts
Author-email: tim@readevalprint.com
License: UNKNOWN
Platform: UNKNOWN
